appchance/__init__.py
appchance/client/__init__.py
appchance/client/api.py
appchance/client/azure.py
appchance/client/ftp.py
appchance/client/graphql.py
appchance/dodos/__init__.py
appchance/dodos/config.py
appchance/dodos/dodo.py
appchance/dodos/tasks/__init__.py
appchance/dodos/tasks/django.py
appchance/multi_db/__init__.py
appchance/multi_db/middleware.py
appchance/multi_db/router.py
appchance/pickup/__init__.py
appchance/pickup/models.py
appchance/sections/__init__.py
appchance/sections/admin.py
appchance/sections/apps.py
appchance/sections/models.py
appchance/sections/querysets.py
appchance/sections/serializers.py
appchance/sections/views.py
appchance/sections/migrations/0001_initial.py
appchance/sections/migrations/__init__.py
appchance/sections/tests/__init__.py
appchance/sections/tests/factories.py
appchance/sections/tests/test_querysets.py
appchance/shop/__init__.py
appchance/shop/models.py
appchance/shop/serializers.py
appchance-0.3.2.0.data/scripts/dodo
integration_tests/__init__.py
integration_tests/sections/__init__.py
integration_tests/sections/manage.py
integration_tests/sections/config/__init__.py
integration_tests/sections/config/settings.py
integration_tests/sections/config/urls.py
integration_tests/sections/config/wsgi.py
integration_tests/sections/sections_app/__init__.py
integration_tests/sections/sections_app/apps.py
integration_tests/sections/sections_app/models.py
integration_tests/sections/sections_app/migrations/0001_initial.py
integration_tests/sections/sections_app/migrations/0002_auto_20201015_1517.py
integration_tests/sections/sections_app/migrations/__init__.py
appchance-0.3.2.0.dist-info/METADATA
appchance-0.3.2.0.dist-info/WHEEL
appchance-0.3.2.0.dist-info/top_level.txt
appchance-0.3.2.0.dist-info/RECORD
