Metadata-Version: 2.1
Name: appchance
Version: 0.3.2.0
Summary: Appchance's spellbook for wizards and ninjas. Useful in dungeons.
Home-page: https://bitbucket.org/appchance/pychance/
Author: Appchance Backend Spellbook
Author-email: backend@appchance.com
License: UNKNOWN
Platform: UNKNOWN
Classifier: Programming Language :: Python :: 3
Classifier: Framework :: Django :: 3.0
Classifier: License :: OSI Approved :: Apache Software License
Classifier: Development Status :: 3 - Alpha
Classifier: Operating System :: POSIX :: Linux
Requires-Python: >=3.7
Requires-Dist: cookiecutter
Requires-Dist: django
Requires-Dist: doit
Requires-Dist: ipython
Requires-Dist: swapper
